[
    {
      "id": "1",
      "accountNo": "11618261826",
      "bankName": "Dutch Bangla Bank",
      "branch": "Madhupur",
      "farmersName": "Mohammad Rahman",
      "fatherName": "Rokon Hossain",
      "location": "31.002,42.002",
      "mobileNo": "01758836798",
      "nid": "768927628",
      "plantation": "8 acres",
      "routingNo": "7838137826",
      "selectedGilla": "Manikgonj",
      "selectedUpjilla": "MKUpjila9",
      "target": "70 kj",
      "village": "Madhupur"
    },
    {
      "id": "2",
      "accountNo": "1234567890",
      "bankName": "Bank Name 2",
      "branch": "Branch 2",
      "farmersName": "John Doe",
      "fatherName": "Father Name 2",
      "location": "31.003,42.003",
      "mobileNo": "01234567890",
      "nid": "123456789",
      "plantation": "10 acres",
      "routingNo": "9876543210",
      "selectedGilla": "Kustia",
      "selectedUpjilla": "KUUpjila6",
      "target": "50 kj",
      "village": "Village 2"
    },
    {
      "id": "3",
      "accountNo": "9876543210",
      "bankName": "Bank Name 3",
      "branch": "Branch 3",
      "farmersName": "Jane Smith",
      "fatherName": "Father Name 3",
      "location": "31.004,42.004",
      "mobileNo": "09876543210",
      "nid": "987654321",
      "plantation": "5 acres",
      "routingNo": "1234567890",
      "selectedGilla": "County 3",
      "selectedUpjilla": "State 3",
      "target": "30 kj",
      "village": "Village 3"
    },
    {
      "id": "4",
      "accountNo": "9876543210",
      "bankName": "Bank Name 3",
      "branch": "Branch 3",
      "farmersName": "Jane Smith",
      "fatherName": "Father Name 3",
      "location": "31.004,42.004",
      "mobileNo": "09876543210",
      "nid": "987654321",
      "plantation": "5 acres",
      "routingNo": "1234567890",
      "selectedGilla": "County 3",
      "selectedUpjilla": "State 3",
      "target": "30 kj",
      "village": "Village 3"
    },
    {
      "id": "5",
      "accountNo": "4567890123",
      "bankName": "Bank Name 4",
      "branch": "Branch 4",
      "farmersName": "Robert Johnson",
      "fatherName": "Father Name 4",
      "location": "31.005,42.005",
      "mobileNo": "04567890123",
      "nid": "456789012",
      "plantation": "3 acres",
      "routingNo": "9012345678",
      "selectedGilla": "County 4",
      "selectedUpjilla": "State 4",
      "target": "20 kj",
      "village": "Village 4"
    }
]